PathPilot/__init__.py
PathPilot/app/PathPilot.py
PathPilot/app/__init__.py
PathPilot/utils/__init__.py
PathPilot/utils/path_util.py
RootWhiz/__init__.py
RootWhiz/app/RootWhiz.py
RootWhiz/app/__init__.py
RootWhiz/utils/__init__.py
RootWhiz/utils/path_util.py
tests/__init__.py
tests/test_PathPilot.py
tests/test_RootWhiz.py
rootwhiz-0.1.0.dist-info/LICENSE
rootwhiz-0.1.0.dist-info/METADATA
rootwhiz-0.1.0.dist-info/WHEEL
rootwhiz-0.1.0.dist-info/top_level.txt
rootwhiz-0.1.0.dist-info/RECORD
