Metadata-Version: 2.1
Name: rootwhiz
Version: 0.1.0
Summary: RootWhiz is a Python package that simplifies directory navigation and path manipulation.
Home-page: https://github.com/justTil/RootWhiz
Author: Til Schwarze
Author-email: til@alatorgenesis.com
Classifier: Programming Language :: Python :: 3
Classifier: License :: OSI Approved :: MIT License
Classifier: Operating System :: OS Independent
Requires-Python: >=3.6
License-File: LICENSE
Requires-Dist: setuptools
